lesson/__init__.py
lesson/const.py
lesson/end.py
lesson/lesson.py
lesson/start.py
lesson/utils.py
lesson-0.0.1.dist-info/DESCRIPTION.rst
lesson-0.0.1.dist-info/METADATA
lesson-0.0.1.dist-info/RECORD
lesson-0.0.1.dist-info/WHEEL
lesson-0.0.1.dist-info/entry_points.txt
lesson-0.0.1.dist-info/metadata.json
lesson-0.0.1.dist-info/top_level.txt
