Metadata-Version: 2.0
Name: lesson
Version: 0.0.1
Summary: A tool for conducting coding lessons
Home-page: https://github.com/defytheflow/lesson
Author: Artyom Danilov
Author-email: defytheflow@gmail.com
License: MIT
Platform: UNKNOWN
